vdaq_ana/AliVATAModule.py
vdaq_ana/Cluster.py
vdaq_ana/GTimer.py
vdaq_ana/Progress.py
vdaq_ana/ScanManager.py
vdaq_ana/TDCAliVATA.py
vdaq_ana/TriggerModule.py
vdaq_ana/VDaqData.py
vdaq_ana/__init__.py
vdaq_ana/cmmds/__init__.py
vdaq_ana/cmmds/analyze_data.py
vdaq_ana/cmmds/getFileInfo.py
vdaq_ana/cmmds/getSpectrum.py
vdaq_ana/cmmds/read_data.py
vdaq_ana/cmmds/show_data.py
vdaq_ana/cmmds/variable_scan.py
vdaq_ana/utils/HistFile.py
vdaq_ana/utils/Histogram.py
vdaq_ana/utils/Histogram2D.py
vdaq_ana/utils/HstStats.py
vdaq_ana/utils/Tracer.py
vdaq_ana/utils/__init__.py
vdaq_ana/utils/fit_utils.py
vdaq_ana/utils/remove_outliers.py
vdaq_ana-0.12.1.dist-info/METADATA
vdaq_ana-0.12.1.dist-info/WHEEL
vdaq_ana-0.12.1.dist-info/entry_points.txt
vdaq_ana-0.12.1.dist-info/top_level.txt
vdaq_ana-0.12.1.dist-info/RECORD
