Metadata-Version: 2.4
Name: vdaq_ana
Version: 0.12.1
Summary: A collection of python scripts to access VDaq data.
Author-email: Carlos Lacasta <carlos.lacasta@alibavasystems.com>
Project-URL: Homepage, https://igit.ific.uv.es
Project-URL: Bug Tracker, https://igit.ific.uv.es
Classifier: Programming Language :: Python :: 3
Classifier: Operating System :: OS Independent
Requires-Python: >=3.7
Requires-Dist: h5py>=3.8.0
Requires-Dist: lmfit>=1.1.0
Requires-Dist: matplotlib>=3.7.1
Requires-Dist: numpy>=1.24.2
Requires-Dist: scipy>=1.10.1
